curation_projects/__init__.py
curation_projects/rgveda.py
video_curation/__init__.py
video_curation/google_api_helper.py
video_curation/video_repo.py
video_curation/youtube_client.py
video_curation-0.0.1.dist-info/METADATA
video_curation-0.0.1.dist-info/RECORD
video_curation-0.0.1.dist-info/WHEEL
video_curation-0.0.1.dist-info/top_level.txt
