Metadata-Version: 2.1
Name: video-curation
Version: 0.0.1
Summary: A package for curating video file collections, with ability to sync with youtube and archive.org video items.
Home-page: https://github.com/sanskrit-coders/video_curation
Author: Sanskrit programmers
Author-email: sanskrit-programmers@googlegroups.com
License: MIT
Keywords: video internet-archive
Platform: UNKNOWN
Classifier: Development Status :: 5 - Production/Stable
Classifier: Intended Audience :: Education
Classifier: Topic :: Text Processing :: Linguistic
Classifier: License :: OSI Approved :: MIT License
Classifier: Programming Language :: Python :: 3
Classifier: Programming Language :: Python :: 3.7
Provides-Extra: test
Requires-Dist: pandas
Requires-Dist: internetarchive
Requires-Dist: audio-curation
Requires-Dist: google
Requires-Dist: python-rest-client
Provides-Extra: test
Requires-Dist: pytest; extra == 'test'
